silizium/__init__.py
silizium/domain/__init__.py
silizium/domain/csv_parser.py
silizium/domain/language.py
silizium/domain/wiki_parser.py
silizium/domain/data/words.csv
silizium/use_cases/__init__.py
silizium/use_cases/silizium_use_cases.py
silizium_binerdy-1.0.1.data/scripts/silizium-cli.py
silizium_binerdy-1.0.1.dist-info/LICENSE
silizium_binerdy-1.0.1.dist-info/METADATA
silizium_binerdy-1.0.1.dist-info/WHEEL
silizium_binerdy-1.0.1.dist-info/top_level.txt
silizium_binerdy-1.0.1.dist-info/RECORD
