Metadata-Version: 2.1
Name: silizium-binerdy
Version: 1.0.1
Summary: Source code for the wiki philosopy game in the module swt fs19
Home-page: https://github.com/binerdy/swt-19fs-silizium
Author: Alan Meile
Author-email: alan.meile@gmail.com
License: UNKNOWN
Platform: UNKNOWN
Classifier: Programming Language :: Python :: 3
Classifier: License :: OSI Approved :: MIT License
Classifier: Operating System :: OS Independent
Requires-Python: >3.6
Requires-Dist: Click (==7.0)
Requires-Dist: coverage (==4.5.3)
Requires-Dist: coveralls (==1.7.0)
Requires-Dist: pytest-bdd (==3.1.0)
Requires-Dist: pytest-cov (==2.6.1)
Requires-Dist: pytest (==4.4.0)
Requires-Dist: selenium (==3.141.0)
